<annotation>
	<folder>simulator_images</folder>
	<filename>image54.jpg</filename>
	<path>/home/ks/robo4-carnd-capstone/data/simulator_images/image54.jpg</path>
	<source>
		<database>Unknown</database>
	</source>
	<size>
		<width>800</width>
		<height>600</height>
		<depth>3</depth>
	</size>
	<segmented>0</segmented>
	<object>
		<name>Red</name>
		<pose>Unspecified</pose>
		<truncated>0</truncated>
		<difficult>0</difficult>
		<bndbox>
			<xmin>109</xmin>
			<ymin>263</ymin>
			<xmax>169</xmax>
			<ymax>394</ymax>
		</bndbox>
	</object>
	<object>
		<name>Red</name>
		<pose>Unspecified</pose>
		<truncated>0</truncated>
		<difficult>0</difficult>
		<bndbox>
			<xmin>374</xmin>
			<ymin>264</ymin>
			<xmax>434</xmax>
			<ymax>395</ymax>
		</bndbox>
	</object>
	<object>
		<name>Red</name>
		<pose>Unspecified</pose>
		<truncated>0</truncated>
		<difficult>0</difficult>
		<bndbox>
			<xmin>643</xmin>
			<ymin>271</ymin>
			<xmax>703</xmax>
			<ymax>402</ymax>
		</bndbox>
	</object>
</annotation>
