<annotation>
	<folder>simulator_images</folder>
	<filename>image261.jpg</filename>
	<path>/home/ks/robo4-carnd-capstone/data/simulator_images/image261.jpg</path>
	<source>
		<database>Unknown</database>
	</source>
	<size>
		<width>800</width>
		<height>600</height>
		<depth>3</depth>
	</size>
	<segmented>0</segmented>
	<object>
		<name>Yellow</name>
		<pose>Unspecified</pose>
		<truncated>0</truncated>
		<difficult>0</difficult>
		<bndbox>
			<xmin>70</xmin>
			<ymin>405</ymin>
			<xmax>107</xmax>
			<ymax>488</ymax>
		</bndbox>
	</object>
	<object>
		<name>Yellow</name>
		<pose>Unspecified</pose>
		<truncated>0</truncated>
		<difficult>0</difficult>
		<bndbox>
			<xmin>233</xmin>
			<ymin>410</ymin>
			<xmax>268</xmax>
			<ymax>493</ymax>
		</bndbox>
	</object>
	<object>
		<name>Yellow</name>
		<pose>Unspecified</pose>
		<truncated>0</truncated>
		<difficult>0</difficult>
		<bndbox>
			<xmin>393</xmin>
			<ymin>412</ymin>
			<xmax>427</xmax>
			<ymax>499</ymax>
		</bndbox>
	</object>
</annotation>
